MANIFEST.in
README.md
setup.py
superlog/__init__.py
superlog/log.py
superlog.egg-info/PKG-INFO
superlog.egg-info/SOURCES.txt
superlog.egg-info/dependency_links.txt
superlog.egg-info/top_level.txt