Metadata-Version: 2.1
Name: superlog
Version: 1.4.2
Summary: Libreria para mostrar mayor cantidad de informacion en los logs de manera facil y poder ser usados en new relic
Home-page: https://github.com/retmago/superlog.git
Author: jsilva95
Author-email: jsilva2018.95@gmail.com
License: LGPL v3
Keywords: log newrelic metadata
Platform: UNKNOWN
Classifier: Programming Language :: Python
Classifier: Programming Language :: Python :: 3.5
Classifier: Programming Language :: Python :: 3.6
Classifier: Programming Language :: Python :: 3.7
Classifier: Programming Language :: Python :: 3.8
